<?xml version="1.0" encoding="UTF-8"?>
<ARTICLE>
<META>
<META_COMMUN>
<ID>LEGIARTI000006575033</ID>
<ANCIEN_ID>PXXXXXXXXXX0056L001AXXAD</ANCIEN_ID>
<ORIGINE>LEGI</ORIGINE>
<URL>article/LEGI/ARTI/00/00/06/57/50/LEGIARTI000006575033.xml</URL>
<NATURE>Article</NATURE>
</META_COMMUN>
<META_SPEC>
<META_ARTICLE>

<NUM>56-1</NUM>

<ETAT>MODIFIE</ETAT>

<DATE_DEBUT>2005-12-13</DATE_DEBUT>
<DATE_FIN>2010-01-06</DATE_FIN>



<TYPE>AUTONOME</TYPE>
</META_ARTICLE>
</META_SPEC>
</META>
<CONTEXTE>
<TEXTE autorite="" cid="LEGITEXT000006071154" date_publi="2999-01-01" date_signature="2999-01-01" ministere="" nature="CODE" nor="" num="" num_parution_jo="">
<TITRE_TXT c_titre_court="Code de procédure pénale" debut="1958-04-08" fin="2999-01-01" id_txt="LEGITEXT000006071154">Code de procédure pénale</TITRE_TXT>
<TM>
<TITRE_TM debut="1958-04-08" fin="2999-01-01" id="LEGISCTA000006098229">Partie législative</TITRE_TM>
<TM>
<TITRE_TM debut="1958-04-08" fin="2013-07-27" id="LEGISCTA000006121321">Livre Ier : De l'exercice de l'action publique et de l'instruction</TITRE_TM>
<TITRE_TM debut="2013-07-27" fin="2999-01-01" id="LEGISCTA000027753875">Livre Ier : De la conduite de la politique pénale, de l'exercice de l'action publique et de l'instruction</TITRE_TM>
<TM>
<TITRE_TM debut="1958-04-08" fin="2999-01-01" id="LEGISCTA000006138089">Titre II : Des enquêtes et des contrôles d'identité</TITRE_TM>
<TM>
<TITRE_TM debut="1958-04-08" fin="2999-01-01" id="LEGISCTA000006151876">Chapitre Ier : Des crimes et des délits flagrants</TITRE_TM>
</TM>
</TM>
</TM>
</TM>
</TEXTE>
</CONTEXTE>

<VERSIONS>
<VERSION etat="MODIFIE">
<LIEN_ART debut="1986-02-01" etat="MODIFIE" fin="1993-03-01" id="LEGIARTI000006575030" num="56-1" origine="LEGI"/>
</VERSION>
<VERSION etat="MODIFIE">
<LIEN_ART debut="1993-03-01" etat="MODIFIE" fin="2000-06-16" id="LEGIARTI000006575031" num="56-1" origine="LEGI"/>
</VERSION>
<VERSION etat="MODIFIE">
<LIEN_ART debut="2000-06-16" etat="MODIFIE" fin="2005-12-13" id="LEGIARTI000006575032" num="56-1" origine="LEGI"/>
</VERSION>
<VERSION etat="MODIFIE">
<LIEN_ART debut="2005-12-13" etat="MODIFIE" fin="2010-01-06" id="LEGIARTI000006575033" num="56-1" origine="LEGI"/>
</VERSION>
<VERSION etat="MODIFIE">
<LIEN_ART debut="2010-01-06" etat="MODIFIE" fin="2019-03-25" id="LEGIARTI000021662499" num="56-1" origine="LEGI"/>
</VERSION>
<VERSION etat="MODIFIE">
<LIEN_ART debut="2019-03-25" etat="MODIFIE" fin="2020-01-01" id="LEGIARTI000038311893" num="56-1" origine="LEGI"/>
</VERSION>
<VERSION etat="MODIFIE">
<LIEN_ART debut="2020-01-01" etat="MODIFIE" fin="2022-03-01" id="LEGIARTI000039279537" num="56-1" origine="LEGI"/>
</VERSION>
<VERSION etat="VIGUEUR">
<LIEN_ART debut="2022-03-01" etat="VIGUEUR" fin="2999-01-01" id="LEGIARTI000044568203" num="56-1" origine="LEGI"/>
</VERSION>
</VERSIONS>
<NOTA>
<CONTENU/>
</NOTA>
<BLOC_TEXTUEL>
<CONTENU>
<br/>Les perquisitions dans le cabinet d'un avocat ou à son domicile ne peuvent être effectuées que par un magistrat et en présence du bâtonnier ou de son délégué, à la suite d'une décision écrite et motivée prise par ce magistrat, qui indique la nature de l'infraction ou des infractions sur lesquelles portent les investigations, les raisons justifiant la perquisition et l'objet de celle-ci. Le contenu de cette décision est porté dès le début de la perquisition à la connaissance du bâtonnier ou de son délégué par le magistrat. Celui-ci et le bâtonnier ou son délégué ont seuls le droit de consulter ou de prendre connaissance des documents se trouvant sur les lieux préalablement à leur éventuelle saisie. Aucune saisie ne peut concerner des documents relatifs à d'autres infractions que celles mentionnées dans la décision précitée. Les dispositions du présent alinéa sont édictées à peine de nullité. <br/>
<br/>Le magistrat qui effectue la perquisition veille à ce que les investigations conduites ne portent pas atteinte au libre exercice de la profession d'avocat. <br/>
<br/>Le bâtonnier ou son délégué peut s'opposer à la saisie d'un document à laquelle le magistrat a l'intention de procéder s'il estime que cette saisie serait irrégulière. Le document doit alors être placé sous scellé fermé. Ces opérations font l'objet d'un procès-verbal mentionnant les objections du bâtonnier ou de son délégué, qui n'est pas joint au dossier de la procédure. Si d'autres documents ont été saisis au cours de la perquisition sans soulever de contestation, ce procès-verbal est distinct de celui prévu par l'article 57. Ce procès-verbal ainsi que le document placé sous scellé fermé sont transmis sans délai au juge des libertés et de la détention, avec l'original ou une copie du dossier de la procédure. <br/>
<br/>Dans les cinq jours de la réception de ces pièces, le juge des libertés et de la détention statue sur la contestation par ordonnance motivée non susceptible de recours.<br/>
<br/>A cette fin, il entend le magistrat qui a procédé à la perquisition et, le cas échéant, le procureur de la République, ainsi que l'avocat au cabinet ou au domicile duquel elle a été effectuée et le bâtonnier ou son délégué. Il peut ouvrir le scellé en présence de ces personnes.<br/>
<br/>S'il estime qu'il n'y a pas lieu à saisir le document, le juge des libertés et de la détention ordonne sa restitution immédiate, ainsi que la destruction du procès-verbal des opérations et, le cas échéant, la cancellation de toute référence à ce document ou à son contenu qui figurerait dans le dossier de la procédure. <br/>
<br/>Dans le cas contraire, il ordonne le versement du scellé et du procès-verbal au dossier de la procédure. Cette décision n'exclut pas la possibilité ultérieure pour les parties de demander la nullité de la saisie devant, selon les cas, la juridiction de jugement ou la chambre de l'instruction. <br/>
<br/>Les dispositions du présent article sont également applicables aux perquisitions effectuées dans les locaux de l'ordre des avocats ou des caisses de règlement pécuniaire des avocats. Dans ce cas, les attributions confiées au juge des libertés et de la détention sont exercées par le président du tribunal de grande instance qui doit être préalablement avisé de la perquisition. Il en est de même en cas de perquisition au cabinet ou au domicile du bâtonnier.<br/>
</CONTENU>
</BLOC_TEXTUEL>
<LIENS>
<LIEN cidtexte="JORFTEXT000000692469" datesignatexte="1957-12-31" id="JORFTEXT000000692469" naturetexte="LOI" nortexte="" num="" numtexte="57-1426" sens="source" typelien="CODIFICATION">Loi 57-1426 1957-12-31</LIEN>
<LIEN cidtexte="JORFTEXT000000786845" datesignatexte="2005-12-12" id="LEGIARTI000006494603" naturetexte="LOI" nortexte="JUSX0407878L" num="37" numtexte="2005-1549" sens="source" typelien="MODIFICATION">Loi n°2005-1549 du 12 décembre 2005 - art. 37 () JORF 13 décembre 2005</LIEN>


















<LIEN cidtexte="LEGITEXT000006071154" datesignatexte="2999-01-01" id="LEGIARTI000006575769" naturetexte="CODE" nortexte="" num="171" numtexte="" sens="cible" typelien="CITATION">CODE DE PROCEDURE PENALE - art. 171 (M)</LIEN>
<LIEN cidtexte="LEGITEXT000006071154" datesignatexte="2999-01-01" id="LEGIARTI000006575488" naturetexte="CODE" nortexte="" num="96" numtexte="" sens="cible" typelien="CITATION">CODE DE PROCEDURE PENALE - art. 96 (V)</LIEN>
<LIEN cidtexte="LEGITEXT000006069565" datesignatexte="2999-01-01" id="LEGIARTI000032224987" naturetexte="CODE" nortexte="" num="L512-61" numtexte="" sens="cible" typelien="CITATION">Code de la consommation - art. L512-61 (VD)</LIEN>
<LIEN cidtexte="LEGITEXT000006071154" datesignatexte="2999-01-01" id="LEGIARTI000038311473" naturetexte="CODE" nortexte="" num="230-34" numtexte="" sens="cible" typelien="CITATION">Code de procédure pénale - art. 230-34 (VD)</LIEN>
<LIEN cidtexte="LEGITEXT000006071154" datesignatexte="2999-01-01" id="LEGIARTI000049778813" naturetexte="CODE" nortexte="" num="56" numtexte="" sens="cible" typelien="CITATION">Code de procédure pénale - art. 56 (V)</LIEN>
<LIEN cidtexte="LEGITEXT000006071154" datesignatexte="2999-01-01" id="LEGIARTI000044550457" naturetexte="CODE" nortexte="" num="56-1-1" numtexte="" sens="cible" typelien="CITATION">Code de procédure pénale - art. 56-1-1 (V)</LIEN>
<LIEN cidtexte="LEGITEXT000006071154" datesignatexte="2999-01-01" id="LEGIARTI000044550454" naturetexte="CODE" nortexte="" num="56-1-2" numtexte="" sens="cible" typelien="CITATION">Code de procédure pénale - art. 56-1-2 (V)</LIEN>
<LIEN cidtexte="LEGITEXT000006071154" datesignatexte="2999-01-01" id="LEGIARTI000032742062" naturetexte="CODE" nortexte="" num="57" numtexte="" sens="cible" typelien="CITATION">Code de procédure pénale - art. 57 (V)</LIEN>
<LIEN cidtexte="LEGITEXT000006071154" datesignatexte="2999-01-01" id="LEGIARTI000047053305" naturetexte="CODE" nortexte="" num="57-1" numtexte="" sens="cible" typelien="CITATION">Code de procédure pénale - art. 57-1 (V)</LIEN>
<LIEN cidtexte="LEGITEXT000006071154" datesignatexte="2999-01-01" id="LEGIARTI000006575045" naturetexte="CODE" nortexte="" num="59" numtexte="" sens="cible" typelien="CITATION">Code de procédure pénale - art. 59 (V)</LIEN>
<LIEN cidtexte="LEGITEXT000006071154" datesignatexte="2999-01-01" id="LEGIARTI000047052970" naturetexte="CODE" nortexte="" num="60-1" numtexte="" sens="cible" typelien="CITATION">Code de procédure pénale - art. 60-1 (V)</LIEN>
<LIEN cidtexte="LEGITEXT000006071154" datesignatexte="2999-01-01" id="LEGIARTI000032655297" naturetexte="CODE" nortexte="" num="695-41" numtexte="" sens="cible" typelien="CITATION">Code de procédure pénale - art. 695-41 (VD)</LIEN>
<LIEN cidtexte="LEGITEXT000006071154" datesignatexte="2999-01-01" id="LEGIARTI000051740331" naturetexte="CODE" nortexte="" num="706-100" numtexte="" sens="cible" typelien="CITATION">Code de procédure pénale - art. 706-100 (V)</LIEN>
<LIEN cidtexte="LEGITEXT000006071154" datesignatexte="2999-01-01" id="LEGIARTI000038311615" naturetexte="CODE" nortexte="" num="706-102-5" numtexte="" sens="cible" typelien="CITATION">Code de procédure pénale - art. 706-102-5 (V)</LIEN>
<LIEN cidtexte="LEGITEXT000006071154" datesignatexte="2999-01-01" id="LEGIARTI000051742876" naturetexte="CODE" nortexte="" num="706-96" numtexte="" sens="cible" typelien="CITATION">Code de procédure pénale - art. 706-96 (V)</LIEN>
<LIEN cidtexte="LEGITEXT000006071154" datesignatexte="2999-01-01" id="LEGIARTI000038311642" naturetexte="CODE" nortexte="" num="706-96-1" numtexte="" sens="cible" typelien="CITATION">Code de procédure pénale - art. 706-96-1 (V)</LIEN>
<LIEN cidtexte="LEGITEXT000006071154" datesignatexte="2999-01-01" id="LEGIARTI000047052915" naturetexte="CODE" nortexte="" num="77-1-1" numtexte="" sens="cible" typelien="CITATION">Code de procédure pénale - art. 77-1-1 (V)</LIEN>
<LIEN cidtexte="LEGITEXT000006071154" datesignatexte="2999-01-01" id="LEGIARTI000045292559" naturetexte="CODE" nortexte="" num="99-3" numtexte="" sens="cible" typelien="CITATION">Code de procédure pénale - art. 99-3 (V)</LIEN>
<LIEN cidtexte="LEGITEXT000006071318" datesignatexte="2999-01-01" id="LEGIARTI000043410469" naturetexte="CODE" nortexte="" num="L232-18-7" numtexte="" sens="cible" typelien="CITATION">Code du sport. - art. L232-18-7 (V)</LIEN>
<LIEN cidtexte="LEGITEXT000006072026" datesignatexte="2999-01-01" id="LEGIARTI000035043690" naturetexte="CODE" nortexte="" num="L621-12" numtexte="" sens="cible" typelien="CITATION">Code monétaire et financier - art. L621-12 (VD)</LIEN>
</LIENS>
</ARTICLE>
