<?xml version="1.0" encoding="UTF-8"?>
<ARTICLE>
<META>
<META_COMMUN>
<ID>KALIARTI000045397076</ID>
<ANCIEN_ID/>
<ORIGINE>KALI</ORIGINE>
<URL>article/KALI/ARTI/00/00/45/39/70/KALIARTI000045397076.xml</URL>
<NATURE>Article</NATURE>
</META_COMMUN>
<META_SPEC>
<META_ARTICLE>

<NUM>22</NUM>
<TITRE>Obligations et priorités d'emploi. Non-discrimination</TITRE>

<ETAT>VIGUEUR_ETEN</ETAT>


<CALIPSOS/>
<HISTORIQUE/>
<DATE_DEBUT>2023-08-01</DATE_DEBUT>
<DATE_FIN>2999-01-01</DATE_FIN>
<DATE_DEB_EXT>2999-01-01</DATE_DEB_EXT>
<DATE_FIN_EXT>2999-01-01</DATE_FIN_EXT>
<TYPE>AUTONOME</TYPE>

</META_ARTICLE>
</META_SPEC>
</META>
<CONTEXTE>
<TEXTE cid="KALITEXT000045397019" date_publi="2999-01-01" date_signature="2021-11-24" nature="Convention collective nationale" nor="ASET2250047M" num="" num_parution_jo="">
<TITRE_TXT c_titre_court="Convention collective nationale du 24 novembre 2021" debut="2023-08-01" fin="2999-01-01" id_txt="KALITEXT000045397019">Convention collective nationale des commerces de quincaillerie, fournitures industrielles, fers, métaux et équipement de la maison du 24 novembre 2021 - Etendue par arrêté du 5 juillet 2023 JORF 13 juillet 2023</TITRE_TXT>


<TM>
<TITRE_TM debut="2023-08-01" fin="2999-01-01" id="KALISCTA000045397026">Chapitre IV Embauche</TITRE_TM>
</TM>
</TEXTE>
<CONTENEUR cid="KALICONT000047839180" date_publi="2023-08-01" etat="VIGUEUR_ETEN" nature="IDCC" num="3243" titre="Convention collective nationale des commerces de quincaillerie, fournitures industrielles, fers, métaux et équipement de la maison du 24 novembre 2021 - Etendue par arrêté du 5 juillet 2023 JORF 13 juillet 2023" url="conteneur/KALI/CONT/00/00/47/83/91/KALICONT000047839180.xml"/>
</CONTEXTE>
<VERSIONS>
<VERSION etat="VIGUEUR_ETEN">
<LIEN_ART debut="2023-08-01" etat="VIGUEUR_ETEN" fin="2999-01-01" id="KALIARTI000045397076" num="22" origine="KALI"/>
</VERSION>
</VERSIONS>
<BLOC_TEXTUEL>
<CONTENU>
<p align="left">Lors de toute embauche, l'employeur s'assurera du respect de ses obligations en matière de priorité de réembauchage.</p>
<p align="left">Il s'assurera de même du respect de ses obligations en matière de priorité d'accès des salariés à temps partiel souhaitant occuper ou reprendre un emploi d'une durée au moins égale à la durée minimale prévue à l'article L. 3123-7 du code du travail ou un emploi à temps complet et des salariés à temps complet souhaitant occuper ou reprendre un emploi à temps partiel.</p>
<p align="left">Il s'assurera également du respect de son obligation d'emploi de travailleurs handicapés, mutilés de guerre et assimilés, mentionnés à l'article L. 5212-13 du code du travail et veillera à l'application de l'annexe relative à l'insertion et à la formation professionnelle des personnes handicapées, à l'application de l'annexe relative à l'égalité professionnelle et salariale entre les femmes et les hommes, ainsi qu'à celle relative à la promotion de la diversité et de l'égalité des chances et de traitement.</p>
<p align="left">De façon générale, aucune personne ne pourra être écartée d'une procédure de recrutement pour l'un des motifs mentionnés à l'article L. 1132-1 du code du travail.</p>
</CONTENU>
</BLOC_TEXTUEL>
<LIENS>

<LIEN cidtexte="LEGITEXT000006072050" datesignatexte="2999-01-01" id="LEGIARTI000006900787" naturetexte="CODE" nortexte="" num="L1132-1" numtexte="" sens="source" typelien="CITATION">Code du travail - art. L1132-1</LIEN>
<LIEN cidtexte="LEGITEXT000006072050" datesignatexte="2999-01-01" id="LEGIARTI000006902547" naturetexte="CODE" nortexte="" num="L3123-7" numtexte="" sens="source" typelien="CITATION">Code du travail - art. L3123-7</LIEN>
<LIEN cidtexte="LEGITEXT000006072050" datesignatexte="2999-01-01" id="LEGIARTI000006903694" naturetexte="CODE" nortexte="" num="L5212-13" numtexte="" sens="source" typelien="CITATION">Code du travail - art. L5212-13</LIEN>
</LIENS>



<INFORMATIONS_COMPLEMENTAIRES>
<CONTENU/>
</INFORMATIONS_COMPLEMENTAIRES>
</ARTICLE>
