<?xml version="1.0" encoding="UTF-8"?>
<SECTION_TA>
<ID>LEGISCTA000027811071</ID>
<TITRE_TA>Section 1 : De la réduction en esclavage et de l'exploitation de personnes réduites en esclavage</TITRE_TA>
<STRUCTURE_TA>
<LIEN_ART debut="2002-01-01" etat="MODIFIE" fin="2013-08-07" id="LEGIARTI000006417811" num="224-1" origine="LEGI"/>
<LIEN_ART debut="1994-03-01" etat="MODIFIE" fin="2002-01-01" id="LEGIARTI000006417810" num="224-1" origine="LEGI"/>
<LIEN_ART debut="1994-03-01" etat="MODIFIE" fin="2013-08-07" id="LEGIARTI000006417812" num="224-2" origine="LEGI"/>
<LIEN_ART debut="1994-03-01" etat="MODIFIE" fin="2004-03-10" id="LEGIARTI000006417813" num="224-3" origine="LEGI"/>
<LIEN_ART debut="2004-03-10" etat="MODIFIE" fin="2013-08-07" id="LEGIARTI000006417814" num="224-3" origine="LEGI"/>
<LIEN_ART debut="1994-03-01" etat="MODIFIE" fin="2013-08-07" id="LEGIARTI000006417815" num="224-4" origine="LEGI"/>
<LIEN_ART debut="1994-03-01" etat="MODIFIE" fin="2013-08-07" id="LEGIARTI000006417816" num="224-5" origine="LEGI"/>
<LIEN_ART debut="2004-03-10" etat="MODIFIE" fin="2013-08-07" id="LEGIARTI000006417817" num="224-5-1" origine="LEGI"/>
<LIEN_ART debut="2004-03-10" etat="MODIFIE" fin="2013-08-07" id="LEGIARTI000006417818" num="224-5-2" origine="LEGI"/>
<LIEN_ART debut="2013-08-07" etat="VIGUEUR" fin="2999-01-01" id="LEGIARTI000027807070" num="224-1 A" origine="LEGI"/>
<LIEN_ART debut="2013-08-07" etat="VIGUEUR" fin="2999-01-01" id="LEGIARTI000027807085" num="224-1 B" origine="LEGI"/>
<LIEN_ART debut="2013-08-07" etat="VIGUEUR" fin="2999-01-01" id="LEGIARTI000027807093" num="224-1 C" origine="LEGI"/>
</STRUCTURE_TA>
<CONTEXTE>
<TEXTE autorite="" cid="LEGITEXT000006070719" date_publi="2999-01-01" date_signature="2999-01-01" ministere="" nature="CODE" nor="" num="" num_parution_jo="">
<TITRE_TXT c_titre_court="Code pénal" debut="1990-09-01" fin="2999-01-01" id_txt="LEGITEXT000006070719">Code pénal</TITRE_TXT>
<TM>
<TITRE_TM debut="1990-09-01" fin="2999-01-01" id="LEGISCTA000006089684">Partie législative</TITRE_TM>
<TM>
<TITRE_TM debut="1992-07-23" fin="2999-01-01" id="LEGISCTA000006117597">Livre II : Des crimes et délits contre les personnes</TITRE_TM>
<TM>
<TITRE_TM debut="1992-07-23" fin="2999-01-01" id="LEGISCTA000006136041">Titre II : Des atteintes à la personne humaine</TITRE_TM>
<TM>
<TITRE_TM debut="1992-07-23" fin="2999-01-01" id="LEGISCTA000006149829">Chapitre IV : Des atteintes aux libertés de la personne</TITRE_TM>
</TM>
</TM>
</TM>
</TM>
</TEXTE>
</CONTEXTE>
</SECTION_TA>
