<?xml version="1.0" encoding="UTF-8"?>
<SECTION_TA>
<ID>LEGISCTA000029221406</ID>
<TITRE_TA>Paragraphe 3 : Dispositions applicables aux matières nucléaires affectées aux moyens nécessaires à la mise en œuvre de la politique de dissuasion</TITRE_TA>
<STRUCTURE_TA>
<LIEN_ART debut="2014-07-12" etat="MODIFIE" fin="2015-06-04" id="LEGIARTI000029227532" num="L1333-14" origine="LEGI"/>
<LIEN_ART debut="2015-06-04" etat="MODIFIE" fin="2015-07-30" id="LEGIARTI000030665881" num="L1333-14" origine="LEGI"/>
<LIEN_ART debut="2015-07-30" etat="VIGUEUR" fin="2999-01-01" id="LEGIARTI000030949378" num="L1333-14" origine="LEGI"/>
</STRUCTURE_TA>
<CONTEXTE>
<TEXTE autorite="" cid="LEGITEXT000006071307" date_publi="2999-01-01" date_signature="2999-01-01" ministere="" nature="CODE" nor="" num="" num_parution_jo="">
<TITRE_TXT c_titre_court="Code de la défense." debut="2004-12-21" fin="2999-01-01" id_txt="LEGITEXT000006071307">Code de la défense</TITRE_TXT>
<TM>
<TITRE_TM debut="2004-12-21" fin="2999-01-01" id="LEGISCTA000006096399">Partie législative</TITRE_TM>
<TM>
<TITRE_TM debut="2004-12-21" fin="2999-01-01" id="LEGISCTA000006120655">PARTIE 1 : PRINCIPES GÉNÉRAUX DE LA DÉFENSE.</TITRE_TM>
<TM>
<TITRE_TM debut="2004-12-21" fin="2999-01-01" id="LEGISCTA000006137702">LIVRE III : MISE EN ŒUVRE DE LA DÉFENSE NON MILITAIRE</TITRE_TM>
<TM>
<TITRE_TM debut="2004-12-21" fin="2999-01-01" id="LEGISCTA000006151475">TITRE III : DÉFENSE ÉCONOMIQUE</TITRE_TM>
<TM>
<TITRE_TM debut="2004-12-21" fin="2999-01-01" id="LEGISCTA000006166901">Chapitre III : Matières et installations nucléaires</TITRE_TM>
<TM>
<TITRE_TM debut="2004-12-21" fin="2999-01-01" id="LEGISCTA000006182572">Section 1 : Protection et contrôle des matières nucléaires</TITRE_TM>
<TM>
<TITRE_TM debut="2014-07-12" fin="2999-01-01" id="LEGISCTA000029221238">Sous-section 3 : Dispositions pénales</TITRE_TM>
</TM>
</TM>
</TM>
</TM>
</TM>
</TM>
</TM>
</TEXTE>
</CONTEXTE>
</SECTION_TA>
